smsaero/__init__.py
smsaero/command_line.py
smsaero_api_async-3.1.0.dist-info/AUTHORS.md
smsaero_api_async-3.1.0.dist-info/LICENSE
smsaero_api_async-3.1.0.dist-info/METADATA
smsaero_api_async-3.1.0.dist-info/WHEEL
smsaero_api_async-3.1.0.dist-info/entry_points.txt
smsaero_api_async-3.1.0.dist-info/top_level.txt
smsaero_api_async-3.1.0.dist-info/RECORD
