Metadata-Version: 2.1
Name: smsaero_api_async
Version: 3.1.0
Summary: SMS Aero Async API client
Home-page: https://github.com/smsaero/smsaero_python/
Author: SMS Aero
Author-email: admin@smsaero.ru
License: MIT
Keywords: smsaero,api,smsaero_api_async,sms,hlr,viber
Classifier: Development Status :: 5 - Production/Stable
Classifier: Environment :: Web Environment
Classifier: Intended Audience :: Developers
Classifier: License :: OSI Approved :: MIT License
Classifier: Operating System :: OS Independent
Classifier: Programming Language :: Python
Classifier: Programming Language :: Python :: 3.7
Classifier: Programming Language :: Python :: 3.8
Classifier: Programming Language :: Python :: 3.9
Classifier: Programming Language :: Python :: 3.10
Classifier: Programming Language :: Python :: 3.11
Classifier: Programming Language :: Python :: 3.12
Classifier: Programming Language :: Python :: 3.13
Classifier: Programming Language :: Python :: 3.14
Classifier: Programming Language :: Python :: Implementation :: CPython
Classifier: Topic :: Software Development :: Libraries :: Python Modules
Classifier: Topic :: Communications :: Telephony
Classifier: Topic :: Internet :: WWW/HTTP
Classifier: Topic :: Software Development :: Libraries :: Python Modules
Requires-Python: >=3.7
License-File: LICENSE
License-File: AUTHORS.md
Requires-Dist: setuptools
Requires-Dist: aiohttp
Provides-Extra: dev
Requires-Dist: pytest >=8.2.2 ; extra == 'dev'
Requires-Dist: flake8 >=7.1.0 ; extra == 'dev'
Requires-Dist: ruff >=0.4.10 ; extra == 'dev'
Requires-Dist: pylint >=3.2.4 ; extra == 'dev'
Requires-Dist: tox >=4.15.1 ; extra == 'dev'
Requires-Dist: mypy >=1.10.0 ; extra == 'dev'
Requires-Dist: coverage >=7.5.4 ; extra == 'dev'
Requires-Dist: bandit >=1.7.9 ; extra == 'dev'
Requires-Dist: build >=1.2.1 ; extra == 'dev'
Requires-Dist: twine >=5.1.1 ; extra == 'dev'
